[{"inputs":[{"internalType":"address","name":"_bhixToken","type":"address"},{"internalType":"address","name":"_usdtToken","type":"address"},{"internalType":"uint256","name":"_startTime","type":"uint256"},{"internalType":"uint256","name":"_endTime","type":"uint256"}],"stateMutability":"nonpayable","type":"constructor"},{"anonymous":false,"inputs":[{"indexed":false,"internalType":"uint256","name":"newPrice","type":"uint256"}],"name":"PriceUpdated","type":"event"},{"anonymous":false,"inputs":[{"indexed":true,"internalType":"address","name":"user","type":"address"},{"indexed":false,"internalType":"uint256","name":"amountBHIX","type":"uint256"},{"indexed":true,"internalType":"address","name":"ref","type":"address"}],"name":"Purchased","type":"event"},{"anonymous":false,"inputs":[{"indexed":false,"internalType":"uint256","name":"bnb","type":"uint256"},{"indexed":false,"internalType":"uint256","name":"usdt","type":"uint256"}],"name":"Withdrawn","type":"event"},{"inputs":[],"name":"bhixToken","outputs":[{"internalType":"contract IBEP20","name":"","type":"address"}],"stateMutability":"view","type":"function"},{"inputs":[{"internalType":"address","name":"_referrer","type":"address"}],"name":"buyWithBNB","outputs":[],"stateMutability":"payable","type":"function"},{"inputs":[{"internalType":"uint256","name":"amount","type":"uint256"},{"internalType":"address","name":"_referrer","type":"address"}],"name":"buyWithUSDT","outputs":[],"stateMutability":"nonpayable","type":"function"},{"inputs":[],"name":"claimReferralReward","outputs":[],"stateMutability":"nonpayable","type":"function"},{"inputs":[{"internalType":"address","name":"","type":"address"}],"name":"contributions","outputs":[{"internalType":"uint256","name":"","type":"uint256"}],"stateMutability":"view","type":"function"},{"inputs":[{"internalType":"uint256","name":"","type":"uint256"}],"name":"contributors","outputs":[{"internalType":"address","name":"","type":"address"}],"stateMutability":"view","type":"function"},{"inputs":[],"name":"endTime","outputs":[{"internalType":"uint256","name":"","type":"uint256"}],"stateMutability":"view","type":"function"},{"inputs":[],"name":"getBNBPrice","outputs":[{"internalType":"uint256","name":"","type":"uint256"}],"stateMutability":"pure","type":"function"},{"inputs":[],"name":"owner","outputs":[{"internalType":"address","name":"","type":"address"}],"stateMutability":"view","type":"function"},{"inputs":[{"internalType":"bool","name":"_status","type":"bool"}],"name":"pausePresale","outputs":[],"stateMutability":"nonpayable","type":"function"},{"inputs":[],"name":"presalePaused","outputs":[{"internalType":"bool","name":"","type":"bool"}],"stateMutability":"view","type":"function"},{"inputs":[{"internalType":"address","name":"","type":"address"}],"name":"referralRewards","outputs":[{"internalType":"uint256","name":"","type":"uint256"}],"stateMutability":"view","type":"function"},{"inputs":[{"internalType":"address","name":"","type":"address"}],"name":"referrer","outputs":[{"internalType":"address","name":"","type":"address"}],"stateMutability":"view","type":"function"},{"inputs":[],"name":"softCap","outputs":[{"internalType":"uint256","name":"","type":"uint256"}],"stateMutability":"view","type":"function"},{"inputs":[],"name":"startTime","outputs":[{"internalType":"uint256","name":"","type":"uint256"}],"stateMutability":"view","type":"function"},{"inputs":[],"name":"tokenPrice","outputs":[{"internalType":"uint256","name":"","type":"uint256"}],"stateMutability":"view","type":"function"},{"inputs":[],"name":"totalRaisedUSD","outputs":[{"internalType":"uint256","name":"","type":"uint256"}],"stateMutability":"view","type":"function"},{"inputs":[{"internalType":"address","name":"newOwner","type":"address"}],"name":"transferOwnership","outputs":[],"stateMutability":"nonpayable","type":"function"},{"inputs":[{"internalType":"uint256","name":"_newEndTime","type":"uint256"}],"name":"updateEndTime","outputs":[],"stateMutability":"nonpayable","type":"function"},{"inputs":[{"internalType":"uint256","name":"_newPrice","type":"uint256"}],"name":"updateTokenPrice","outputs":[],"stateMutability":"nonpayable","type":"function"},{"inputs":[],"name":"usdtToken","outputs":[{"internalType":"contract IBEP20","name":"","type":"address"}],"stateMutability":"view","type":"function"},{"inputs":[],"name":"withdrawFunds","outputs":[],"stateMutability":"nonpayable","type":"function"},{"stateMutability":"payable","type":"receive"}]
